README.md
setup.py
video_transcode/__init__.py
video_transcode/video_transcode.py
video_transcode.egg-info/PKG-INFO
video_transcode.egg-info/SOURCES.txt
video_transcode.egg-info/dependency_links.txt
video_transcode.egg-info/entry_points.txt
video_transcode.egg-info/not-zip-safe
video_transcode.egg-info/requires.txt
video_transcode.egg-info/top_level.txt
video_transcode/config/Makefile
video_transcode/config/celery.conf
video_transcode/config/config.yaml
video_transcode/config/video-transcode.service.template