Metadata-Version: 2.1
Name: video-transcode
Version: 1.6.0
Summary: Video commercial cutting and transcoding stack.
Home-page: https://github.com/kirbs-/video-transcode
Author: Chris Kirby
Author-email: kirbycm@gmail.com
License: MIT
Platform: UNKNOWN
